flask_jsonpify.py
setup.py
Flask_Jsonpify.egg-info/PKG-INFO
Flask_Jsonpify.egg-info/SOURCES.txt
Flask_Jsonpify.egg-info/dependency_links.txt
Flask_Jsonpify.egg-info/not-zip-safe
Flask_Jsonpify.egg-info/requires.txt
Flask_Jsonpify.egg-info/top_level.txt