Metadata-Version: 1.0
Name: Flask-Jsonpify
Version: 1.1
Summary: A simple Flask extension extending Flask's core jsonify functionality to support JSON-Padded responses, using the callback specified in the querystring
Home-page: https://github.com/wcdolphin/flask-jsonpify
Author: Cory Dolphin
Author-email: wcdolphin@gmail.com
License: MIT
Platform: any
Classifier: Environment :: Web Environment
Classifier: Intended Audience :: Developers
Classifier: License :: OSI Approved :: BSD License
Classifier: Operating System :: OS Independent
Classifier: Programming Language :: Python
Classifier: Topic :: Internet :: WWW/HTTP :: Dynamic Content
Classifier: Topic :: Software Development :: Libraries :: Python Modules
